README.md
setup.py
test/__init__.py
test/test_account.py
test/test_account_detail.py
test/test_account_reassigned.py
test/test_account_request.py
test/test_account_response.py
test/test_account_spid.py
test/test_address_company.py
test/test_amount_request.py
test/test_authorization_transaction_group.py
test/test_authorized_beneficiaries_response.py
test/test_authorized_users.py
test/test_autorizacin_de_depsitos_api.py
test/test_balance.py
test/test_balance_list_response.py
test/test_beneficiaries_query_register_status.py
test/test_beneficiaries_response.py
test/test_beneficiary_dto.py
test/test_beneficiary_institution.py
test/test_billing.py
test/test_billing_transaction.py
test/test_cargos_recurrentes_api.py
test/test_cep_response.py
test/test_cep_search_banxico.py
test/test_certificate_request.py
test/test_codi_code_qr_response_dto.py
test/test_codi_code_request_dto.py
test/test_codi_operation_response_dto.py
test/test_codi_operations_filters_request_dto.py
test/test_company_registered.py
test/test_company_requested.py
test/test_compay.py
test/test_comprobante_electrnico_de_pago__cep_api.py
test/test_configurations_limits.py
test/test_confirm_recurring_charge.py
test/test_contact_request.py
test/test_contacto_api.py
test/test_contract_detail_request.py
test/test_contract_detail_response.py
test/test_contracts_details_api.py
test/test_cuentas_de_beneficiarios_spei_api.py
test/test_cuentas_de_beneficiarios_spid_api.py
test/test_customer.py
test/test_deposit.py
test/test_deposit_authorization_request.py
test/test_depositant.py
test/test_depositant_count_response.py
test/test_depositantes_api.py
test/test_depositants_register.py
test/test_depositants_response.py
test/test_deposits_authorization_response.py
test/test_detailed_error_response.py
test/test_empresas_co_di_api.py
test/test_error_response.py
test/test_facturas_api.py
test/test_failed_charges_data_dto.py
test/test_get_depositants.py
test/test_instituciones_api.py
test/test_institution.py
wire4_client.egg-info/PKG-INFO
wire4_client.egg-info/SOURCES.txt
wire4_client.egg-info/dependency_links.txt
wire4_client.egg-info/requires.txt
wire4_client.egg-info/top_level.txt
