Metadata-Version: 2.1
Name: wire4-client
Version: 1.1.4
Summary: Wire4RestAPI
Home-page: 
Author-email: 
Keywords: Swagger,Wire4RestAPI
